README.rst
setup.cfg
setup.py
properties_image/__init__.py
properties_image/images.py
properties_image.egg-info/PKG-INFO
properties_image.egg-info/SOURCES.txt
properties_image.egg-info/dependency_links.txt
properties_image.egg-info/requires.txt
properties_image.egg-info/top_level.txt