Metadata-Version: 1.1
Name: properties-image
Version: 0.0.1
Summary: properties_image
Home-page: http://steno3d.com/
Author: 3point Science
Author-email: info@3ptscience.com
License: UNKNOWN
Download-URL: http://github.com/3ptscience/properties-image
Keywords: property
Platform: Windows
Platform: Linux
Platform: Solaris
Platform: Mac OS-X
Platform: Unix
Classifier: Development Status :: 4 - Beta
Classifier: Programming Language :: Python
Classifier: Topic :: Scientific/Engineering
Classifier: Topic :: Scientific/Engineering :: Mathematics
Classifier: Topic :: Scientific/Engineering :: Physics
Classifier: Operating System :: Microsoft :: Windows
Classifier: Operating System :: POSIX
Classifier: Operating System :: Unix
Classifier: Operating System :: MacOS
Classifier: Natural Language :: English
